README.md
ext/.gitkeep
ext/darwin_aarch64/libfliptengine.dylib
ext/darwin_x86_64/libfliptengine.dylib
ext/flipt_engine.h
ext/linux_aarch64/libfliptengine.so
ext/linux_x86_64/libfliptengine.so
ext/windows_x86_64/fliptengine.dll
flipt_client/__init__.py
flipt_client/errors.py
flipt_client/models.py
flipt_client-1.4.1.dist-info/LICENSE
flipt_client-1.4.1.dist-info/METADATA
flipt_client-1.4.1.dist-info/WHEEL
flipt_client-1.4.1.dist-info/RECORD
