Metadata-Version: 2.1
Name: flipt-client
Version: 1.4.1
Summary: Flipt Client Evaluation SDK
Home-page: https://github.com/flipt-io/flipt-client-sdks
License: MIT
Author: Flipt Devs
Author-email: dev@flipt.io
Requires-Python: >=3.8,<4.0
Classifier: License :: OSI Approved :: MIT License
Classifier: Programming Language :: Python :: 3
Classifier: Programming Language :: Python :: 3.8
Classifier: Programming Language :: Python :: 3.9
Classifier: Programming Language :: Python :: 3.10
Classifier: Programming Language :: Python :: 3.11
Classifier: Programming Language :: Python :: 3.12
Requires-Dist: packaging (>=24,<26)
Requires-Dist: pydantic (>=1.10,<3.0)
Project-URL: Repository, https://github.com/flipt-io/flipt-client-sdks
